{
 "actions": [],
 "creation": "2026-05-19 00:00:00.000000",
 "doctype": "DocType",
 "editable_grid": 1,
 "engine": "InnoDB",
 "field_order": [
  "transaction_date",
  "payment_category",
  "reference",
  "narration",
  "party",
  "amount",
  "account",
  "bank_transaction",
  "payment_entry",
  "sales_invoice",
  "match_status"
 ],
 "fields": [
  {
   "fieldname": "transaction_date",
   "fieldtype": "Date",
   "in_list_view": 1,
   "label": "Transaction Date"
  },
  {
   "fieldname": "payment_category",
   "fieldtype": "Select",
   "in_list_view": 1,
   "label": "Payment Category",
   "options": "Bank Transfer\nCard / POS\nMobile Money\nOther"
  },
  {
   "fieldname": "reference",
   "fieldtype": "Data",
   "in_list_view": 1,
   "label": "Reference"
  },
  {
   "fieldname": "narration",
   "fieldtype": "Small Text",
   "label": "Narration"
  },
  {
   "fieldname": "party",
   "fieldtype": "Data",
   "label": "Party"
  },
  {
   "fieldname": "amount",
   "fieldtype": "Currency",
   "in_list_view": 1,
   "label": "Amount"
  },
  {
   "fieldname": "account",
   "fieldtype": "Link",
   "label": "Account",
   "options": "Account"
  },
  {
   "fieldname": "bank_transaction",
   "fieldtype": "Link",
   "label": "Bank Transaction",
   "options": "Bank Transaction"
  },
  {
   "fieldname": "payment_entry",
   "fieldtype": "Link",
   "label": "Payment Entry",
   "options": "Payment Entry"
  },
  {
   "fieldname": "sales_invoice",
   "fieldtype": "Link",
   "label": "Sales Invoice",
   "options": "Sales Invoice"
  },
  {
   "default": "Pending",
   "fieldname": "match_status",
   "fieldtype": "Select",
   "label": "Match Status",
   "options": "Pending\nCandidate Match\nMatched for Review\nIgnored"
  }
 ],
 "istable": 1,
 "module": "RetailEdge",
 "name": "RetailEdge Statement Import Row",
 "owner": "Administrator"
}
